win10toast/__init__.py
win10toast/__main__.py
win10toast/data/python.ico
win10toast_persist/__init__.py
win10toast_persist/data/python.ico
win10toast_persist-0.10.1.dist-info/LICENSE
win10toast_persist-0.10.1.dist-info/METADATA
win10toast_persist-0.10.1.dist-info/WHEEL
win10toast_persist-0.10.1.dist-info/top_level.txt
win10toast_persist-0.10.1.dist-info/RECORD
